src/server.py
message_server_april_2023-0.0.1.dist-info/METADATA
message_server_april_2023-0.0.1.dist-info/WHEEL
message_server_april_2023-0.0.1.dist-info/top_level.txt
message_server_april_2023-0.0.1.dist-info/RECORD
