Metadata-Version: 2.1
Name: message-server-april-2023
Version: 0.0.1
Summary: message_server_april_2023
Author: Sego
Author-email: grayg@mail.ru
Requires-Dist: PyQt5
Requires-Dist: sqlalchemy
Requires-Dist: pycryptodome
Requires-Dist: pycryptodomex
